LICENSE
README.md
setup.cfg
setup.py
outerloop/__init__.py
outerloop/kernels.py
outerloop/priors.py
outerloop/transforms.py
outerloop.egg-info/PKG-INFO
outerloop.egg-info/SOURCES.txt
outerloop.egg-info/dependency_links.txt
outerloop.egg-info/top_level.txt