Metadata-Version: 2.1
Name: outerloop
Version: 0.0.1
Summary: Hands-on Bayesian Optimization for hyperparameter search
Home-page: https://github.com/outerloopxyz/outerloop
Author: Marcus Lewis
License-File: LICENSE
